{"cameraMode":{"drawMode":0,"name":"Shaded","section":"Shading Mode"},"sceneLighting":true,"audioPlay":false,"sceneViewState":{"showFog":true,"showMaterialUpdate":false,"showSkybox":true,"showFlares":true,"showImageEffects":true,"showParticleSystems":true},"in2DMode":false,"pivot":{"x":-829.5931396484375,"y":-420.868408203125,"z":-1026.916748046875},"rotation":{"x":-0.22656072676181794,"y":0.279323935508728,"z":-0.06800295412540436,"w":-0.9306050539016724},"size":4323.86865234375,"orthographic":false}